mininn/__init__.py
mininn/convertor.py
mininn/mininn_capi.pyd
mininn/predictor.py
mininn/mininn_fbs/Attribute.py
mininn/mininn_fbs/Graph.py
mininn/mininn_fbs/Node.py
mininn/mininn_fbs/Op.py
mininn/mininn_fbs/Tensor.py
mininn/mininn_fbs/__init__.py
mininn-1.2.0.dist-info/METADATA
mininn-1.2.0.dist-info/WHEEL
mininn-1.2.0.dist-info/top_level.txt
mininn-1.2.0.dist-info/RECORD
