Metadata-Version: 2.4
Name: mininn
Version: 1.2.0
Summary: python interface of MiniNN
Author: masteryi-0018
Author-email: <1536474741@qq.com>
Requires-Dist: onnxruntime
Requires-Dist: onnx
Dynamic: author
Dynamic: author-email
Dynamic: description
Dynamic: requires-dist
Dynamic: summary
